pdf2packet/pdf2packet.py
pdf2packet-0.0.11.dist-info/LICENSE
pdf2packet-0.0.11.dist-info/METADATA
pdf2packet-0.0.11.dist-info/WHEEL
pdf2packet-0.0.11.dist-info/entry_points.txt
pdf2packet-0.0.11.dist-info/top_level.txt
pdf2packet-0.0.11.dist-info/RECORD
